django_essence/__init__.py
django_essence/managers.py
django_essence/models.py
django_essence-0.1.0.dist-info/LICENSE
django_essence-0.1.0.dist-info/METADATA
django_essence-0.1.0.dist-info/WHEEL
django_essence-0.1.0.dist-info/top_level.txt
django_essence-0.1.0.dist-info/RECORD
